{
  "project_info": {
    "project_number": "1077338476919",
    "firebase_url": "https://kitchenideas-2228a.firebaseio.com",
    "project_id": "kitchenideas-2228a",
    "storage_bucket": "kitchenideas-2228a.appspot.com"
  },
  "client": [
    {
      "client_info": {
        "mobilesdk_app_id": "1:1077338476919:android:c6cbedbffa445e67",
        "android_client_info": {
          "package_name": "com.rebenko.mykitchenideas"
        }
      },
      "oauth_client": [
        {
          "client_id": "1077338476919-00ilba3a8q4t5816i2mcr5m1ld1mrbea.apps.googleusercontent.com",
          "client_type": 3
        }
      ],
      "api_key": [
        {
          "current_key": "AIzaSyAegZX39Vjw00rjlmmuNSpADxgZcDlL_NY"
        }
      ],
      "services": {
        "analytics_service": {
          "status": 1
        },
        "appinvite_service": {
          "status": 1,
          "other_platform_oauth_client": []
        },
        "ads_service": {
          "status": 2
        }
      }
    }
  ],
  "configuration_version": "1"
}